essaid/grpc/tims/v0/tims_pb2.py
essaid/grpc/tims/v0/tims_pb2.pyi
essaid/grpc/tims/v0/tims_pb2_grpc.py
tims_grpc-0.0.2.dist-info/METADATA
tims_grpc-0.0.2.dist-info/WHEEL
tims_grpc-0.0.2.dist-info/RECORD
